pytunelogix/__init__.py
pytunelogix/exe.py
pytunelogix/clxpidsim/__init__.py
pytunelogix/clxpidsim/clxsim.py
pytunelogix/common/__init__.py
pytunelogix/common/generalclasses.py
pytunelogix/pidlogger/__init__.py
pytunelogix/pidlogger/clxlogger.py
pytunelogix/simulate/__init__.py
pytunelogix/simulate/simulator.py
pytunelogix/stage1/__init__.py
pytunelogix/stage1/csvtuner.py
pytunelogix/stage2/__init__.py
pytunelogix/stage2/openlooptune.py
pytunelogix/stage3/__init__.py
pytunelogix/stage3/closedlooptune.py
pytunelogix/stage4/__init__.py
pytunelogix/stage4/adaptivetune.py
pytunelogix-1.1.19.dist-info/METADATA
pytunelogix-1.1.19.dist-info/WHEEL
pytunelogix-1.1.19.dist-info/top_level.txt
pytunelogix-1.1.19.dist-info/RECORD
