Metadata-Version: 2.1
Name: pytunelogix
Version: 1.1.19
Summary: PID tuner, logger and simulator
Home-page: https://github.com/Destination2Unknown/pytunelogix
Author: Destination2Unknown
Author-email: destination0b10unknown@gmail.com
License: MIT
Keywords: PID Tuner
Platform: UNKNOWN
Classifier: Development Status :: 5 - Production/Stable
Classifier: Intended Audience :: Information Technology
Classifier: Programming Language :: Python :: 3.7
Classifier: Programming Language :: Python :: 3.8
Classifier: Programming Language :: Python :: 3.9
Classifier: Programming Language :: Python :: 3.10
Classifier: Operating System :: MacOS :: MacOS X
Classifier: Operating System :: Microsoft :: Windows
Requires-Dist: scipy
Requires-Dist: numpy
Requires-Dist: matplotlib
Requires-Dist: pylogix
Requires-Dist: pandas
